careermapblock/__init__.py
careermapblock/models.py
careermapblock/urls.py
careermapblock/views.py
careermapblock/templates/careermapblock/careermapblock.html
careermapblock/templates/careermapblock/careermapblock_css.html
careermapblock/templates/careermapblock/careermapblock_js.html
careermapblock/templates/careermapblock/edit_basemap.html
careermapblock/templates/careermapblock/edit_basemaps.html
careermapblock/templates/careermapblock/edit_counties.html
careermapblock/templates/careermapblock/edit_county.html
careermapblock/templates/careermapblock/edit_county_stat_type.html
careermapblock/templates/careermapblock/edit_county_stat_types.html
careermapblock/templates/careermapblock/edit_layer.html
careermapblock/templates/careermapblock/edit_layers.html
careermapblock/templates/careermapblock/edit_question.html
careermapblock/templates/careermapblock/edit_questions.html
django_careermapblock-0.4.0.dist-info/DESCRIPTION.rst
django_careermapblock-0.4.0.dist-info/METADATA
django_careermapblock-0.4.0.dist-info/RECORD
django_careermapblock-0.4.0.dist-info/WHEEL
django_careermapblock-0.4.0.dist-info/metadata.json
django_careermapblock-0.4.0.dist-info/top_level.txt
