Metadata-Version: 2.0
Name: django-careermapblock
Version: 0.4.0
Summary: Career Map Activity PageBlock
Home-page: UNKNOWN
Author: Anders Pearson
Author-email: anders@columbia.edu
License: BSD
Platform: any
